sxnti/__init__.py
sxnti/operaciones.py
sxnti-0.1.dist-info/LICENSE
sxnti-0.1.dist-info/METADATA
sxnti-0.1.dist-info/WHEEL
sxnti-0.1.dist-info/top_level.txt
sxnti-0.1.dist-info/RECORD
